{"type":"FeatureCollection","features":[{"type":"Feature","properties":{"name":"poppleton"},"geometry":{"coordinates":[-1.141025,53.988014],"type":"Point"}},{"type":"Feature","properties":{"name":"corndogs"},"geometry":{"coordinates":[-1.080074,53.959366],"type":"Point"}}]}
